station/.dockerignore
station/__init__.py
station/app/__init__.py
station/app/api/__init__.py
station/app/api/api_v1/__init__.py
station/app/api/api_v1/api.py
station/app/api/api_v1/endpoints/__init__.py
station/app/api/api_v1/endpoints/airflow.py
station/app/api/api_v1/endpoints/datasets.py
station/app/api/api_v1/endpoints/docker_trains.py
station/app/api/api_v1/endpoints/fhir.py
station/app/api/api_v1/endpoints/local_trains.py
station/app/api/api_v1/endpoints/master_images.py
station/app/api/api_v1/endpoints/notifications.py
station/app/api/api_v1/endpoints/station.py
station/app/api/api_v1/endpoints/station_status.py
station/app/api/dependencies.py
station/app/auth.py
station/app/cache.py
station/app/clients.py
station/app/config.py
station/app/crud/__init__.py
station/app/crud/base.py
station/app/crud/crud_datasets.py
station/app/crud/crud_discovery.py
station/app/crud/crud_docker_trains.py
station/app/crud/crud_fhir_servers.py
station/app/crud/crud_local_train.py
station/app/crud/crud_notifications.py
station/app/crud/crud_train_configs.py
station/app/crud/local_train_master_image.py
station/app/datasets/__init__.py
station/app/datasets/filesystem.py
station/app/datasets/statistics.py
station/app/db/__init__.py
station/app/db/base.py
station/app/db/base_class.py
station/app/db/session.py
station/app/db/setup_db.py
station/app/env.py
station/app/fhir/__init__.py
station/app/fhir/server.py
station/app/logger.py
station/app/main.py
station/app/models/__init__.py
station/app/models/datasets.py
station/app/models/discovery.py
station/app/models/docker_trains.py
station/app/models/fhir_server.py
station/app/models/local_trains.py
station/app/models/notification.py
station/app/run_station.py
station/app/schemas/__init__.py
station/app/schemas/airflow.py
station/app/schemas/datasets.py
station/app/schemas/discovery.py
station/app/schemas/dl_models.py
station/app/schemas/docker_trains.py
station/app/schemas/fhir.py
station/app/schemas/local_trains.py
pht_station-0.2.2.dist-info/METADATA
pht_station-0.2.2.dist-info/WHEEL
pht_station-0.2.2.dist-info/entry_points.txt
pht_station-0.2.2.dist-info/RECORD
