Metadata-Version: 2.1
Name: pht-station
Version: 0.2.2
Summary: Python library for handling containerized PHT trains
Author: Michael Graf
Author-email: michael.graf@uni-tuebingen.com
Requires-Python: >=3.10,<4.0
Classifier: Programming Language :: Python :: 3
Classifier: Programming Language :: Python :: 3.10
Classifier: Programming Language :: Python :: 3.11
Requires-Dist: SQLAlchemy
Requires-Dist: authup (>=0.5.0,<0.6.0)
Requires-Dist: click
Requires-Dist: cryptography
Requires-Dist: docker
Requires-Dist: fastapi[all]
Requires-Dist: fhir-kindling
Requires-Dist: jinja2
Requires-Dist: loguru
Requires-Dist: minio
Requires-Dist: numpy
Requires-Dist: pandas
Requires-Dist: pht-train-container-library
Requires-Dist: plotly
Requires-Dist: psutil
Requires-Dist: psycopg2-binary
Requires-Dist: pycryptodome
Requires-Dist: python-keycloak
Requires-Dist: python-multipart
Requires-Dist: redis
Requires-Dist: requests
Requires-Dist: rich
